MANIFEST.in
README.md
setup.cfg
setup.py
harix/__init__.py
harix/__version__.py
harix.egg-info/PKG-INFO
harix.egg-info/SOURCES.txt
harix.egg-info/dependency_links.txt
harix.egg-info/requires.txt
harix.egg-info/top_level.txt
harix/rdk/__init__.py
harix/rdk/harix_api/__init__.py
harix/rdk/harix_api/motion/__init__.py
harix/rdk/harix_api/motion/robot_control_api.py
harix/rdk/harix_api/navagation/__init__.py
harix/rdk/harix_api/navagation/robot_navigate_api.py
harix/rdk/harix_api/nlu/__init__.py
harix/rdk/harix_api/nlu/nlu.py
harix/rdk/harix_api/operate/__init__.py
harix/rdk/harix_api/operate/robot_config_api.py
harix/rdk/harix_api/robotmind/RobotMindServer.py
harix/rdk/harix_api/robotmind/RobotMindService.py
harix/rdk/harix_api/robotmind/__init__.py
harix/rdk/harix_api/subscribe/__init__.py
harix/rdk/harix_api/subscribe/robot_subscribe.py
harix/rdk/harix_api/subscribe/subscribe.py
harix/rdk/harix_api/vision/VisionServer.py
harix/rdk/harix_api/vision/VisionService.py
harix/rdk/harix_api/vision/__init__.py
harix/rdk/harix_api/vision/vision.py
harix/rdk/harix_api/voice/SpeechServer.py
harix/rdk/harix_api/voice/SpeechService.py
harix/rdk/harix_api/voice/__init__.py
harix/rdk/harix_api/voice/robot_tts_api.py
harix/rdk/nlu/__init__.py
harix/rdk/nlu/nlu.py
harix/rdk/proto/__init__.py
harix/rdk/proto/common/__init__.py
harix/rdk/proto/common/common_pb2.py
harix/rdk/proto/common/common_pb2_grpc.py
harix/rdk/proto/common/imageType_pb2.py
harix/rdk/proto/common/imageType_pb2_grpc.py
harix/rdk/proto/common/qa_pb2.py
harix/rdk/proto/common/qa_pb2_grpc.py
harix/rdk/proto/common/sw_common_pb2.py
harix/rdk/proto/common/sw_common_pb2_grpc.py
harix/rdk/proto/nlu/__init__.py
harix/rdk/proto/nlu/nlu_pb2.py
harix/rdk/proto/nlu/nlu_pb2_grpc.py
harix/rdk/proto/robot_mind/__init__.py
harix/rdk/proto/robot_mind/robotmind_pb2.py
harix/rdk/proto/robot_mind/robotmind_pb2_grpc.py
harix/rdk/proto/robot_mind/robotskill_pb2.py
harix/rdk/proto/robot_mind/robotskill_pb2_grpc.py
harix/rdk/proto/robot_skill_api/__init__.py
harix/rdk/proto/robot_skill_api/robot_config_api_pb2.py
harix/rdk/proto/robot_skill_api/robot_config_api_pb2_grpc.py
