Metadata-Version: 2.1
Name: harix
Version: 1.0.8
Summary: CloudMinds robot develop kit.
Home-page: https://www.cloudminds.com
Author: CloudMinds
Author-email: harix@cloudminds.com
License: MIT
Keywords: robot development kit CloudMinds HARIX
Platform: UNKNOWN
Classifier: License :: OSI Approved :: MIT License
Classifier: Programming Language :: Python
Classifier: Programming Language :: Python :: 3
Classifier: Programming Language :: Python :: 3.7
Classifier: Programming Language :: Python :: Implementation :: CPython
Classifier: Programming Language :: Python :: Implementation :: PyPy
Requires-Python: >=3.5.1
